<?xml version="1.0" encoding="UTF-8"?>
<MetaDataObject xmlns="http://v8.1c.ru/8.3/MDClasses" xmlns:app="http://v8.1c.ru/8.2/managed-application/core" xmlns:cfg="http://v8.1c.ru/8.1/data/enterprise/current-config" xmlns:cmi="http://v8.1c.ru/8.2/managed-application/cmi" xmlns:ent="http://v8.1c.ru/8.1/data/enterprise" xmlns:lf="http://v8.1c.ru/8.2/managed-application/logform" xmlns:style="http://v8.1c.ru/8.1/data/ui/style" xmlns:sys="http://v8.1c.ru/8.1/data/ui/fonts/system" xmlns:v8="http://v8.1c.ru/8.1/data/core" xmlns:v8ui="http://v8.1c.ru/8.1/data/ui" xmlns:web="http://v8.1c.ru/8.1/data/ui/colors/web" xmlns:win="http://v8.1c.ru/8.1/data/ui/colors/windows" xmlns:xen="http://v8.1c.ru/8.3/xcf/enums" xmlns:xpr="http://v8.1c.ru/8.3/xcf/predef" xmlns:xr="http://v8.1c.ru/8.3/xcf/readable" xmlns:xs="http://www.w3.org/2001/XMLSchema" xmlns:xsi="http://www.w3.org/2001/XMLSchema-instance" version="2.15">
	<Document uuid="2ea863b7-cbf6-484a-9185-2cfaa50bf51b">
		<InternalInfo>
			<xr:GeneratedType name="DocumentObject.Документ97" category="Object">
				<xr:TypeId>4e306a8c-e7b8-4fdd-9480-cc877f583e92</xr:TypeId>
				<xr:ValueId>28723d97-d0e6-4ea1-800a-147427edd750</xr:ValueId>
			</xr:GeneratedType>
			<xr:GeneratedType name="DocumentRef.Документ97" category="Ref">
				<xr:TypeId>c44b8248-0bea-4e95-b431-8ebe6b3de238</xr:TypeId>
				<xr:ValueId>ab9ef8b8-e33a-414f-bb86-4d5e3fe2a22e</xr:ValueId>
			</xr:GeneratedType>
			<xr:GeneratedType name="DocumentSelection.Документ97" category="Selection">
				<xr:TypeId>280ba1df-2e81-4cef-a98d-88a4bebb4088</xr:TypeId>
				<xr:ValueId>9c23a6fe-4bd5-4e43-b883-ea5cc985b035</xr:ValueId>
			</xr:GeneratedType>
			<xr:GeneratedType name="DocumentList.Документ97" category="List">
				<xr:TypeId>f45c498e-06cd-4efa-a97e-04a093759da2</xr:TypeId>
				<xr:ValueId>0ddb944c-d16c-40ea-a397-7792895fdb74</xr:ValueId>
			</xr:GeneratedType>
			<xr:GeneratedType name="DocumentManager.Документ97" category="Manager">
				<xr:TypeId>e4971d6c-a533-4fab-901a-cac2e4d74247</xr:TypeId>
				<xr:ValueId>978e017d-d8c0-4286-9dbc-c631d90552a4</xr:ValueId>
			</xr:GeneratedType>
		</InternalInfo>
		<Properties>
			<Name>Документ97</Name>
			<Synonym/>
			<Comment/>
			<UseStandardCommands>true</UseStandardCommands>
			<Numerator/>
			<NumberType>String</NumberType>
			<NumberLength>9</NumberLength>
			<NumberAllowedLength>Variable</NumberAllowedLength>
			<NumberPeriodicity>Nonperiodical</NumberPeriodicity>
			<CheckUnique>true</CheckUnique>
			<Autonumbering>true</Autonumbering>
			<Characteristics/>
			<BasedOn/>
			<InputByString>
				<xr:Field>Document.Документ97.StandardAttribute.Number</xr:Field>
			</InputByString>
			<CreateOnInput>Use</CreateOnInput>
			<SearchStringModeOnInputByString>Begin</SearchStringModeOnInputByString>
			<FullTextSearchOnInputByString>DontUse</FullTextSearchOnInputByString>
			<ChoiceDataGetModeOnInputByString>Directly</ChoiceDataGetModeOnInputByString>
			<DefaultObjectForm>Document.Документ97.Form.ФормаДокумента</DefaultObjectForm>
			<DefaultListForm/>
			<DefaultChoiceForm/>
			<AuxiliaryObjectForm/>
			<AuxiliaryListForm/>
			<AuxiliaryChoiceForm/>
			<Posting>Allow</Posting>
			<RealTimePosting>Allow</RealTimePosting>
			<RegisterRecordsDeletion>AutoDeleteOnUnpost</RegisterRecordsDeletion>
			<RegisterRecordsWritingOnPost>WriteSelected</RegisterRecordsWritingOnPost>
			<SequenceFilling>AutoFill</SequenceFilling>
			<RegisterRecords/>
			<PostInPrivilegedMode>true</PostInPrivilegedMode>
			<UnpostInPrivilegedMode>true</UnpostInPrivilegedMode>
			<IncludeHelpInContents>false</IncludeHelpInContents>
			<DataLockFields/>
			<DataLockControlMode>Managed</DataLockControlMode>
			<FullTextSearch>Use</FullTextSearch>
			<ObjectPresentation/>
			<ExtendedObjectPresentation/>
			<ListPresentation/>
			<ExtendedListPresentation/>
			<Explanation/>
			<ChoiceHistoryOnInput>Auto</ChoiceHistoryOnInput>
			<DataHistory>DontUse</DataHistory>
			<UpdateDataHistoryImmediatelyAfterWrite>false</UpdateDataHistoryImmediatelyAfterWrite>
			<ExecuteAfterWriteDataHistoryVersionProcessing>false</ExecuteAfterWriteDataHistoryVersionProcessing>
		</Properties>
		<ChildObjects>
			<Attribute uuid="bf8810fd-0353-4601-8885-16c07f5eeb31">
				<Properties>
					<Name>Ветеринар</Name>
					<Synonym>
						<v8:item>
							<v8:lang>ru</v8:lang>
							<v8:content>Ветеринар</v8:content>
						</v8:item>
					</Synonym>
					<Comment/>
					<Type>
						<v8:Type>cfg:CatalogRef.Сотрудники</v8:Type>
					</Type>
					<PasswordMode>false</PasswordMode>
					<Format/>
					<EditFormat/>
					<ToolTip/>
					<MarkNegatives>false</MarkNegatives>
					<Mask/>
					<MultiLine>false</MultiLine>
					<ExtendedEdit>false</ExtendedEdit>
					<MinValue xsi:nil="true"/>
					<MaxValue xsi:nil="true"/>
					<FillFromFillingValue>false</FillFromFillingValue>
					<FillValue xsi:nil="true"/>
					<FillChecking>DontCheck</FillChecking>
					<ChoiceFoldersAndItems>Items</ChoiceFoldersAndItems>
					<ChoiceParameterLinks/>
					<ChoiceParameters/>
					<QuickChoice>Auto</QuickChoice>
					<CreateOnInput>Auto</CreateOnInput>
					<ChoiceForm/>
					<LinkByType/>
					<ChoiceHistoryOnInput>Auto</ChoiceHistoryOnInput>
					<Indexing>DontIndex</Indexing>
					<FullTextSearch>Use</FullTextSearch>
					<DataHistory>Use</DataHistory>
				</Properties>
			</Attribute>
			<Attribute uuid="bc03001d-5e69-4cb4-a48e-532853b416db">
				<Properties>
					<Name>Питомец</Name>
					<Synonym>
						<v8:item>
							<v8:lang>ru</v8:lang>
							<v8:content>Питомец</v8:content>
						</v8:item>
					</Synonym>
					<Comment/>
					<Type>
						<v8:Type>cfg:CatalogRef.Питомцы</v8:Type>
					</Type>
					<PasswordMode>false</PasswordMode>
					<Format/>
					<EditFormat/>
					<ToolTip/>
					<MarkNegatives>false</MarkNegatives>
					<Mask/>
					<MultiLine>false</MultiLine>
					<ExtendedEdit>false</ExtendedEdit>
					<MinValue xsi:nil="true"/>
					<MaxValue xsi:nil="true"/>
					<FillFromFillingValue>false</FillFromFillingValue>
					<FillValue xsi:nil="true"/>
					<FillChecking>DontCheck</FillChecking>
					<ChoiceFoldersAndItems>Items</ChoiceFoldersAndItems>
					<ChoiceParameterLinks/>
					<ChoiceParameters/>
					<QuickChoice>Auto</QuickChoice>
					<CreateOnInput>Auto</CreateOnInput>
					<ChoiceForm/>
					<LinkByType/>
					<ChoiceHistoryOnInput>Auto</ChoiceHistoryOnInput>
					<Indexing>DontIndex</Indexing>
					<FullTextSearch>Use</FullTextSearch>
					<DataHistory>Use</DataHistory>
				</Properties>
			</Attribute>
			<Form>ФормаДокумента</Form>
		</ChildObjects>
	</Document>
</MetaDataObject>